streamlit_talk/__init__.py
streamlit_talk/frontend/build/asset-manifest.json
streamlit_talk/frontend/build/bootstrap.min.css
streamlit_talk/frontend/build/bootstrap.min.css.map
streamlit_talk/frontend/build/index.html
streamlit_talk/frontend/build/precache-manifest.f9e25907feb1350d455cd4a0aeb888b9.js
streamlit_talk/frontend/build/service-worker.js
streamlit_talk/frontend/build/static/js/2.5fcf9f35.chunk.js
streamlit_talk/frontend/build/static/js/2.5fcf9f35.chunk.js.LICENSE.txt
streamlit_talk/frontend/build/static/js/2.5fcf9f35.chunk.js.map
streamlit_talk/frontend/build/static/js/main.25cb62a4.chunk.js
streamlit_talk/frontend/build/static/js/main.25cb62a4.chunk.js.map
streamlit_talk/frontend/build/static/js/runtime-main.11ec9aca.js
streamlit_talk/frontend/build/static/js/runtime-main.11ec9aca.js.map
streamlit_talk-0.1.9.dist-info/LICENSE
streamlit_talk-0.1.9.dist-info/METADATA
streamlit_talk-0.1.9.dist-info/WHEEL
streamlit_talk-0.1.9.dist-info/top_level.txt
streamlit_talk-0.1.9.dist-info/RECORD
