Metadata-Version: 2.1
Name: streamlit-talk
Version: 0.1.9
Summary: A streamlit component, to make a UI for chat messages in Streamlit
Home-page: https://github.com/yichern/st-chat
Author: Yi Chern Tan
Author-email: tanyichern.accs@gmail.com
Keywords: chat talk streamlit streamlit-component
Classifier: Programming Language :: Python :: 3
Classifier: Operating System :: OS Independent
Requires-Python: >=3.8
License-File: LICENSE
Requires-Dist: streamlit (>=0.63)
